oauth2_provider/__init__.py
oauth2_provider/admin.py
oauth2_provider/apps.py
oauth2_provider/backends.py
oauth2_provider/checks.py
oauth2_provider/compat.py
oauth2_provider/decorators.py
oauth2_provider/exceptions.py
oauth2_provider/forms.py
oauth2_provider/generators.py
oauth2_provider/http.py
oauth2_provider/middleware.py
oauth2_provider/models.py
oauth2_provider/oauth2_backends.py
oauth2_provider/oauth2_validators.py
oauth2_provider/scopes.py
oauth2_provider/settings.py
oauth2_provider/signals.py
oauth2_provider/urls.py
oauth2_provider/utils.py
oauth2_provider/validators.py
oauth2_provider/contrib/__init__.py
oauth2_provider/contrib/rest_framework/__init__.py
oauth2_provider/contrib/rest_framework/authentication.py
oauth2_provider/contrib/rest_framework/permissions.py
oauth2_provider/management/__init__.py
oauth2_provider/management/commands/__init__.py
oauth2_provider/management/commands/cleartokens.py
oauth2_provider/management/commands/createapplication.py
oauth2_provider/migrations/0001_initial.py
oauth2_provider/migrations/0002_auto_20190406_1805.py
oauth2_provider/migrations/0003_auto_20201211_1314.py
oauth2_provider/migrations/0004_auto_20200902_2022.py
oauth2_provider/migrations/0005_auto_20211222_2352.py
oauth2_provider/migrations/0006_alter_application_client_secret.py
oauth2_provider/migrations/0007_application_post_logout_redirect_uris.py
oauth2_provider/migrations/0008_alter_accesstoken_token.py
oauth2_provider/migrations/0009_add_hash_client_secret.py
oauth2_provider/migrations/0010_application_allowed_origins.py
oauth2_provider/migrations/0011_refreshtoken_token_family.py
oauth2_provider/migrations/0012_add_token_checksum.py
oauth2_provider/migrations/__init__.py
oauth2_provider/templates/oauth2_provider/application_confirm_delete.html
oauth2_provider/templates/oauth2_provider/application_detail.html
oauth2_provider/templates/oauth2_provider/application_form.html
oauth2_provider/templates/oauth2_provider/application_list.html
django_oauth_toolkit-3.0.0.dist-info/AUTHORS
django_oauth_toolkit-3.0.0.dist-info/LICENSE
django_oauth_toolkit-3.0.0.dist-info/METADATA
django_oauth_toolkit-3.0.0.dist-info/WHEEL
django_oauth_toolkit-3.0.0.dist-info/top_level.txt
django_oauth_toolkit-3.0.0.dist-info/RECORD
