Metadata-Version: 2.1
Name: django-oauth-toolkit
Version: 3.0.0
Summary: OAuth2 Provider for Django
Author: Federico Frenguelli, Massimiliano Pippi
Author-email: synasius@gmail.com
License: Copyright (c) 2013, Massimiliano Pippi, Federico Frenguelli and contributors
Project-URL: Homepage, https://django-oauth-toolkit.readthedocs.io/
Project-URL: Repository, https://github.com/jazzband/django-oauth-toolkit
Keywords: django,oauth,oauth2,oauthlib
Classifier: Development Status :: 5 - Production/Stable
Classifier: Environment :: Web Environment
Classifier: Framework :: Django
Classifier: Framework :: Django :: 4.2
Classifier: Framework :: Django :: 5.0
Classifier: Framework :: Django :: 5.1
Classifier: Intended Audience :: Developers
Classifier: License :: OSI Approved :: BSD License
Classifier: Operating System :: OS Independent
Classifier: Programming Language :: Python :: 3
Classifier: Programming Language :: Python :: 3.8
Classifier: Programming Language :: Python :: 3.9
Classifier: Programming Language :: Python :: 3.10
Classifier: Programming Language :: Python :: 3.11
Classifier: Programming Language :: Python :: 3.12
Classifier: Topic :: Internet :: WWW/HTTP
Requires-Python: >=3.8
License-File: LICENSE
License-File: AUTHORS
Requires-Dist: django >=4.2
Requires-Dist: requests >=2.13.0
Requires-Dist: oauthlib >=3.2.2
Requires-Dist: jwcrypto >=1.5.0
